{"cameraMode":{"drawMode":0,"name":"Shaded","section":"Shading Mode"},"sceneLighting":true,"audioPlay":false,"sceneViewState":{"m_AlwaysRefresh":false,"showFog":true,"showSkybox":true,"showFlares":true,"showImageEffects":true,"showParticleSystems":true,"showVisualEffectGraphs":true,"m_FxEnabled":true},"in2DMode":false,"pivot":{"x":-7.158044338226318,"y":1.9277557134628297,"z":-2.332634687423706},"rotation":{"x":-0.15551377832889558,"y":-0.7434948682785034,"z":0.18551847338676454,"w":-0.6234289407730103},"size":1.2408292293548585,"orthographic":false}